DiSL Lab/Lab3/prog4.v
module prog4(a, b, c, d, f);
	input a, b, c, d;
	output f;
	nand(A, a, a);
	nand(B, b, b);
	nand(D, d, d);
	nand(p, A, B);
	nand(q, B, D);
	nand(r, c, d);
	nand(f, p, q, r);
endmodule

DiSL Lab/Lab3/prog4_tb.v
`timescale 1ns/1ns
`include "prog4.v"//Name of the Verilog file
module prog4_tb();
reg a, b, c, d;//Input
wire f;//Output
prog4 p4(a, b, c, d, f); //Instantiation of the module
initial
begin
    $dumpfile("prog4_tb.vcd");
    $dumpvars(0, prog4_tb);
    a=1'b0; b=1'b0; c=1'b0; d=1'b0;
    #10
    a=1'b0; b=1'b0; c=1'b0; d=1'b1;
    #10
    a=1'b0; b=1'b0; c=1'b1; d=1'b0;
    #10
    a=1'b0; b=1'b0; c=1'b1; d=1'b1;
    #10
    a=1'b0; b=1'b1; c=1'b0; d=1'b0;
    #10
    a=1'b0; b=1'b1; c=1'b0; d=1'b1;
    #10
    a=1'b0; b=1'b1; c=1'b1; d=1'b0;
    #10
    a=1'b0; b=1'b1; c=1'b1; d=1'b1;
    #10
    a=1'b1; b=1'b0; c=1'b0; d=1'b0;
    #10
    a=1'b1; b=1'b0; c=1'b0; d=1'b1;
    #10
    a=1'b1; b=1'b0; c=1'b1; d=1'b0;
    #10
    a=1'b1; b=1'b0; c=1'b1; d=1'b1;
    #10
    a=1'b1; b=1'b1; c=1'b0; d=1'b0;
    #10
    a=1'b1; b=1'b1; c=1'b0; d=1'b1;
    #10
    a=1'b1; b=1'b1; c=1'b1; d=1'b0;
    #10
    a=1'b1; b=1'b1; c=1'b1; d=1'b1;
    #10
    $display("Test complete");
end
endmodule

DiSL Lab/Lab3/prog4_tb.vcd
$date
	Thu Aug 13 09:39:53 2026
$end
$version
	Icarus Verilog
$end
$timescale
	1ns
$end
$scope module prog4_tb $end
$var wire 1 ! f $end
$var reg 1 " a $end
$var reg 1 # b $end
$var reg 1 $ c $end
$var reg 1 % d $end
$scope module p4 $end
$var wire 1 & A $end
$var wire 1 ' B $end
$var wire 1 ( D $end
$var wire 1 " a $end
$var wire 1 # b $end
$var wire 1 $ c $end
$var wire 1 % d $end
$var wire 1 ! f $end
$var wire 1 ) p $end
$var wire 1 * q $end
$var wire 1 + r $end
$upscope $end
$upscope $end
$enddefinitions $end
#0
$dumpvars
1+
0*
0)
1(
1'
1&
0%
0$
0#
0"
1!
$end
#10
1*
0(
1%
#20
0*
1(
0%
1$
#30
1*
0(
0+
1%
#40
0!
1)
1(
1+
0'
0%
0$
1#
#50
0(
1%
#60
1(
0%
1$
#70
1!
0(
0+
1%
#80
0*
1(
1+
1'
0&
0%
0$
0#
1"
#90
0!
1*
0(
1%
#100
1!
0*
1(
0%
1$
#110
1*
0(
0+
1%
#120
0!
1(
1+
0'
0%
0$
1#
#130
0(
1%
#140
1(
0%
1$
#150
1!
0(
0+
1%
