DiSL Lab/Lab3/prog1.v
module prog1(a, b, c, d, f);
	input a, b, c, d;
	output f;

	//Gate level primitives
	nand(p, b, b);
	nand(q, d, d);
	nand(x, a, p);
	nand(y, c, q);
	nand(z, x, y);
	nand(f, z, z);
endmodule

DiSL Lab/Lab2/prog1_tb.v
`timescale 1ns/1ns
`include "prog1.v"//Name of the Verilog file
module prog1_tb();
reg a, b, c, d;//Input
wire f;//Output
prog1 p1(a, b, c, d, f); //Instantiation of the module
initial
begin
    $dumpfile("prog1_tb.vcd");
    $dumpvars(0, prog1_tb);
    a=1'b0; b=1'b0; c=1'b0; d=1'b0;
    #10
    a=1'b0; b=1'b0; c=1'b0; d=1'b1;
    #10
    a=1'b0; b=1'b0; c=1'b1; d=1'b0;
    #10
    a=1'b0; b=1'b0; c=1'b1; d=1'b1;
    #10
    a=1'b0; b=1'b1; c=1'b0; d=1'b0;
    #10
    a=1'b0; b=1'b1; c=1'b0; d=1'b1;
    #10
    a=1'b0; b=1'b1; c=1'b1; d=1'b0;
    #10
    a=1'b0; b=1'b1; c=1'b1; d=1'b1;
    #10
    a=1'b1; b=1'b0; c=1'b0; d=1'b0;
    #10
    a=1'b1; b=1'b0; c=1'b0; d=1'b1;
    #10
    a=1'b1; b=1'b0; c=1'b1; d=1'b0;
    #10
    a=1'b1; b=1'b0; c=1'b1; d=1'b1;
    #10
    a=1'b1; b=1'b1; c=1'b0; d=1'b0;
    #10
    a=1'b1; b=1'b1; c=1'b0; d=1'b1;
    #10
    a=1'b1; b=1'b1; c=1'b1; d=1'b0;
    #10
    a=1'b1; b=1'b1; c=1'b1; d=1'b1;
    #10
    $display("Test complete");
end
endmodule

DiSL Lab/Lab3/prog1_tb.vcd
$date
	Thu Aug 13 09:24:07 2026
$end
$version
	Icarus Verilog
$end
$timescale
	1ns
$end
$scope module prog1_tb $end
$var wire 1 ! f $end
$var reg 1 " a $end
$var reg 1 # b $end
$var reg 1 $ c $end
$var reg 1 % d $end
$scope module p1 $end
$var wire 1 " a $end
$var wire 1 # b $end
$var wire 1 $ c $end
$var wire 1 % d $end
$var wire 1 ! f $end
$var wire 1 & p $end
$var wire 1 ' q $end
$var wire 1 ( x $end
$var wire 1 ) y $end
$var wire 1 * z $end
$upscope $end
$upscope $end
$enddefinitions $end
#0
$dumpvars
0*
1)
1(
1'
1&
0%
0$
0#
0"
1!
$end
#10
0'
1%
#20
0!
1*
0)
1'
0%
1$
#30
1!
0*
1)
0'
1%
#40
1'
0&
0%
0$
1#
#50
0'
1%
#60
0!
1*
0)
1'
0%
1$
#70
1!
0*
1)
0'
1%
#80
0!
1*
0(
1'
1&
0%
0$
0#
1"
#90
0'
1%
#100
0)
1'
0%
1$
#110
1)
0'
1%
#120
1!
0*
1(
1'
0&
0%
0$
1#
#130
0'
1%
#140
0!
1*
0)
1'
0%
1$
#150
1!
0*
1)
0'
1%
