DiSL Lab/Lab3/prog2.v
module prog2(a, b, c, d, f);
	input a, b, c, d;
	output f;

	//Gate level primitives
	nor(p, a, a);
	nor(q, b, b);
	nor(r, c, c);
	nor(s, d, d);
	nor(x, q, d);
	nor(y, p, q);
	nor(z, r, s);
	nor(f, x, y, z);
endmodule

DiSL Lab/Lab3/prog2_tb.v
`timescale 1ns/1ns
`include "prog2.v"//Name of the Verilog file
module prog2_tb();
reg a, b, c, d;//Input
wire f;//Output
prog2 p2(a, b, c, d, f); //Instantiation of the module
initial
begin
    $dumpfile("prog2_tb.vcd");
    $dumpvars(0, prog2_tb);
    a=1'b0; b=1'b0; c=1'b0; d=1'b0;
    #10
    a=1'b0; b=1'b0; c=1'b0; d=1'b1;
    #10
    a=1'b0; b=1'b0; c=1'b1; d=1'b0;
    #10
    a=1'b0; b=1'b0; c=1'b1; d=1'b1;
    #10
    a=1'b0; b=1'b1; c=1'b0; d=1'b0;
    #10
    a=1'b0; b=1'b1; c=1'b0; d=1'b1;
    #10
    a=1'b0; b=1'b1; c=1'b1; d=1'b0;
    #10
    a=1'b0; b=1'b1; c=1'b1; d=1'b1;
    #10
    a=1'b1; b=1'b0; c=1'b0; d=1'b0;
    #10
    a=1'b1; b=1'b0; c=1'b0; d=1'b1;
    #10
    a=1'b1; b=1'b0; c=1'b1; d=1'b0;
    #10
    a=1'b1; b=1'b0; c=1'b1; d=1'b1;
    #10
    a=1'b1; b=1'b1; c=1'b0; d=1'b0;
    #10
    a=1'b1; b=1'b1; c=1'b0; d=1'b1;
    #10
    a=1'b1; b=1'b1; c=1'b1; d=1'b0;
    #10
    a=1'b1; b=1'b1; c=1'b1; d=1'b1;
    #10
    $display("Test complete");
end
endmodule

DiSL Lab/Lab3/prog2_tb.vcd
$date
	Thu Aug 13 09:25:27 2026
$end
$version
	Icarus Verilog
$end
$timescale
	1ns
$end
$scope module prog2_tb $end
$var wire 1 ! f $end
$var reg 1 " a $end
$var reg 1 # b $end
$var reg 1 $ c $end
$var reg 1 % d $end
$scope module p2 $end
$var wire 1 " a $end
$var wire 1 # b $end
$var wire 1 $ c $end
$var wire 1 % d $end
$var wire 1 ! f $end
$var wire 1 & p $end
$var wire 1 ' q $end
$var wire 1 ( r $end
$var wire 1 ) s $end
$var wire 1 * x $end
$var wire 1 + y $end
$var wire 1 , z $end
$upscope $end
$upscope $end
$enddefinitions $end
#0
$dumpvars
0,
0+
0*
1)
1(
1'
1&
0%
0$
0#
0"
1!
$end
#10
0)
1%
#20
1)
0(
0%
1$
#30
0!
1,
0)
1%
#40
0,
1)
1*
1(
0'
0%
0$
1#
#50
1!
0)
0*
1%
#60
0!
1)
1*
0(
0%
1$
#70
1,
0!
0)
0*
1%
#80
1!
0,
1)
1(
1'
0&
0%
0$
0#
1"
#90
0)
1%
#100
1)
0(
0%
1$
#110
0!
1,
0)
1%
#120
0,
1+
1)
1*
1(
0'
0%
0$
1#
#130
0)
0*
1%
#140
1)
1*
0(
0%
1$
#150
1,
0)
0*
1%
