DiSL Lab/Lab1/prog1.v
module prog1(a, b, c, d, f);
	input a, b, c, d;
	output f;

	//Gate level primitives
	and (h, a, b);
	nor (i, h, c);
	or (j, h, c);
	and (k, i, d);
	or (l, j, d);
	and (f, k, l);

	//Continuous assignment statement
	//assign f = ((~((a & b) | (c))) & (d)) & (((a & b) | (c)) | (d));
endmodule

DiSL Lab/Lab2/prog1_tb.v
`timescale 1ns/1ns
`include "prog1.v"//Name of the Verilog file
module prog1_tb();
reg a, b, c, d;//Input
wire f;//Output
prog1 p1(a, b, c, d, f); //Instantiation of the module
initial
begin
    $dumpfile("prog1_tb.vcd");
    $dumpvars(0, prog1_tb);
    a=1'b0; b=1'b0; c=1'b0; d=1'b0;
    #10
    a=1'b0; b=1'b0; c=1'b0; d=1'b1;
    #10
    a=1'b0; b=1'b0; c=1'b1; d=1'b0;
    #10
    a=1'b0; b=1'b0; c=1'b1; d=1'b1;
    #10
    a=1'b0; b=1'b1; c=1'b0; d=1'b0;
    #10
    a=1'b0; b=1'b1; c=1'b0; d=1'b1;
    #10
    a=1'b0; b=1'b1; c=1'b1; d=1'b0;
    #10
    a=1'b0; b=1'b1; c=1'b1; d=1'b1;
    #10
    a=1'b1; b=1'b0; c=1'b0; d=1'b0;
    #10
    a=1'b1; b=1'b0; c=1'b0; d=1'b1;
    #10
    a=1'b1; b=1'b0; c=1'b1; d=1'b0;
    #10
    a=1'b1; b=1'b0; c=1'b1; d=1'b1;
    #10
    a=1'b1; b=1'b1; c=1'b0; d=1'b0;
    #10
    a=1'b1; b=1'b1; c=1'b0; d=1'b1;
    #10
    a=1'b1; b=1'b1; c=1'b1; d=1'b0;
    #10
    a=1'b1; b=1'b1; c=1'b1; d=1'b1;
    #10
    $display("Test complete");
end
endmodule

DiSL Lab/Lab1/prog1_tb.vcd
$date
	Thu Jul 30 09:27:52 2026
$end
$version
	Icarus Verilog
$end
$timescale
	1ns
$end
$scope module prog1_tb $end
$var wire 1 ! f $end
$var reg 1 " a $end
$var reg 1 # b $end
$var reg 1 $ c $end
$var reg 1 % d $end
$scope module p1 $end
$var wire 1 " a $end
$var wire 1 # b $end
$var wire 1 $ c $end
$var wire 1 % d $end
$var wire 1 ! f $end
$var wire 1 & h $end
$var wire 1 ' i $end
$var wire 1 ( j $end
$var wire 1 ) k $end
$var wire 1 * l $end
$upscope $end
$upscope $end
$enddefinitions $end
#0
$dumpvars
0*
0)
0(
1'
0&
0%
0$
0#
0"
0!
$end
#10
1!
1)
1*
1%
#20
0!
0)
0'
1(
0%
1$
#30
1%
#40
0*
1'
0(
0%
0$
1#
#50
1!
1)
1*
1%
#60
0!
0)
0'
1(
0%
1$
#70
1%
#80
0*
1'
0(
0%
0$
0#
1"
#90
1!
1)
1*
1%
#100
0!
0)
0'
1(
0%
1$
#110
1%
#120
1&
0%
0$
1#
#130
1%
#140
0%
1$
#150
1%
