DiSL Lab/Lab1/prog2.v
module prog2(a, b, c, d, f, g);

	//Gate level primitives
	input a, b, c, d;
	output f, g;
	nand (h, a, b);
	xor (f, h, c, d);
	nor (g, b, c, d);

	//Continuous assignment statement
	//assign f = (a ~& b) ^ (d) ^ (c);
	//assign g = (b ~| c ~| d);
endmodule

DiSL Lab/Lab1/prog2_tb.v
`timescale 1ns/1ns
`include "prog2.v"//Name of the Verilog file
module prog2_tb();
reg a, b, c, d;//Input
wire f, g;//Output
prog2 p2(a, b, c, d, f, g); //Instantiation of the module
initial
begin
    $dumpfile("prog2_tb.vcd");
    $dumpvars(0, prog2_tb);
    a=1'b0; b=1'b0; c=1'b0; d=1'b0;
    #10
    a=1'b0; b=1'b0; c=1'b0; d=1'b1;
    #10
    a=1'b0; b=1'b0; c=1'b1; d=1'b0;
    #10
    a=1'b0; b=1'b0; c=1'b1; d=1'b1;
    #10
    a=1'b0; b=1'b1; c=1'b0; d=1'b0;
    #10
    a=1'b0; b=1'b1; c=1'b0; d=1'b1;
    #10
    a=1'b0; b=1'b1; c=1'b1; d=1'b0;
    #10
    a=1'b0; b=1'b1; c=1'b1; d=1'b1;
    #10
    a=1'b1; b=1'b0; c=1'b0; d=1'b0;
    #10
    a=1'b1; b=1'b0; c=1'b0; d=1'b1;
    #10
    a=1'b1; b=1'b0; c=1'b1; d=1'b0;
    #10
    a=1'b1; b=1'b0; c=1'b1; d=1'b1;
    #10
    a=1'b1; b=1'b1; c=1'b0; d=1'b0;
    #10
    a=1'b1; b=1'b1; c=1'b0; d=1'b1;
    #10
    a=1'b1; b=1'b1; c=1'b1; d=1'b0;
    #10
    a=1'b1; b=1'b1; c=1'b1; d=1'b1;
    #10
    $display("Test complete");
end
endmodule

DiSL Lab/Lab1/prog2_tb.vcd
$date
	Thu Jul 30 09:37:56 2026
$end
$version
	Icarus Verilog
$end
$timescale
	1ns
$end
$scope module prog2_tb $end
$var wire 1 ! g $end
$var wire 1 " f $end
$var reg 1 # a $end
$var reg 1 $ b $end
$var reg 1 % c $end
$var reg 1 & d $end
$scope module p2 $end
$var wire 1 # a $end
$var wire 1 $ b $end
$var wire 1 % c $end
$var wire 1 & d $end
$var wire 1 " f $end
$var wire 1 ! g $end
$var wire 1 ' h $end
$upscope $end
$upscope $end
$enddefinitions $end
#0
$dumpvars
1'
0&
0%
0$
0#
1"
1!
$end
#10
0"
0!
1&
#20
0&
1%
#30
1"
1&
#40
0&
0%
1$
#50
0"
1&
#60
0&
1%
#70
1"
1&
#80
1!
0&
0%
0$
1#
#90
0"
0!
1&
#100
0&
1%
#110
1"
1&
#120
0"
0'
0&
0%
1$
#130
1"
1&
#140
0&
1%
#150
0"
1&
