DiSL Lab/Lab1/prog3.v
module prog3(a, b, c, f1, f2);
	input a, b, c;
	output f1, f2;
	assign f1 = ((a & ~c) | (b & c) | (~b & ~c));
	assign f2 = ((a | ~b | c) & (a | b | ~c) & (~a | b | ~c));
endmodule

DiSL Lab/Lab1/prog3_tb.v
`timescale 1ns/1ns
`include "prog3.v"//Name of the Verilog file
module prog3_tb();
reg a, b, c;//Input
wire f1, f2;//Output
prog3 p3(a, b, c, f1, f2); //Instantiation of the module
initial
begin
    $dumpfile("prog3_tb.vcd");
    $dumpvars(0, prog3_tb);
    a=1'b0; b=1'b0; c=1'b0;
    #10
    a=1'b0; b=1'b0; c=1'b1;
    #10
    a=1'b0; b=1'b1; c=1'b0;
    #10
    a=1'b0; b=1'b1; c=1'b1;
    #10
    a=1'b1; b=1'b0; c=1'b0;
    #10
    a=1'b1; b=1'b0; c=1'b1;
    #10
    a=1'b1; b=1'b1; c=1'b0;
    #10
    a=1'b1; b=1'b1; c=1'b1;
    #10
    $display("Test complete");
end
endmodule

DiSL Lab/Lab1/prog3_tb.vcd
$date
	Thu Jul 30 09:48:29 2026
$end
$version
	Icarus Verilog
$end
$timescale
	1ns
$end
$scope module prog3_tb $end
$var wire 1 ! f2 $end
$var wire 1 " f1 $end
$var reg 1 # a $end
$var reg 1 $ b $end
$var reg 1 % c $end
$scope module p3 $end
$var wire 1 # a $end
$var wire 1 $ b $end
$var wire 1 % c $end
$var wire 1 " f1 $end
$var wire 1 ! f2 $end
$upscope $end
$upscope $end
$enddefinitions $end
#0
$dumpvars
0%
0$
0#
1"
1!
$end
#10
0!
0"
1%
#20
0!
0%
1$
#30
1"
1!
1%
#40
0%
0$
1#
#50
0"
0!
1%
#60
1"
1!
0%
1$
#70
1%
