DiSL Lab/Lab2/prog5.v
module prog5(a, b, c, d, f);
	input a, b, c, d;
	output f;
	assign f = a&b&d | a&b&c | b&c&d | a&c&d;

	//Gate Level Assignment
	// and (p, a, b, d);
	// and (q, a, b, c);
	// and (r, b, c, d);
	// and (s, a, c, d);
	// or (f, p, q, r, s);
endmodule

DiSL Lab/Lab2/prog5_tb.v
`timescale 1ns/1ns
`include "prog5.v"//Name of the Verilog file
module prog5_tb();
reg a, b, c, d;//Input
wire f;//Output
prog5 p5(a, b, c, d, f); //Instantiation of the module
initial
begin
    $dumpfile("prog5_tb.vcd");
    $dumpvars(0, prog5_tb);
    a=1'b0; b=1'b0; c=1'b0; d=1'b0;
    #10
    a=1'b0; b=1'b0; c=1'b0; d=1'b1;
    #10
    a=1'b0; b=1'b0; c=1'b1; d=1'b0;
    #10
    a=1'b0; b=1'b0; c=1'b1; d=1'b1;
    #10
    a=1'b0; b=1'b1; c=1'b0; d=1'b0;
    #10
    a=1'b0; b=1'b1; c=1'b0; d=1'b1;
    #10
    a=1'b0; b=1'b1; c=1'b1; d=1'b0;
    #10
    a=1'b0; b=1'b1; c=1'b1; d=1'b1;
    #10
    a=1'b1; b=1'b0; c=1'b0; d=1'b0;
    #10
    a=1'b1; b=1'b0; c=1'b0; d=1'b1;
    #10
    a=1'b1; b=1'b0; c=1'b1; d=1'b0;
    #10
    a=1'b1; b=1'b0; c=1'b1; d=1'b1;
    #10
    a=1'b1; b=1'b1; c=1'b0; d=1'b0;
    #10
    a=1'b1; b=1'b1; c=1'b0; d=1'b1;
    #10
    a=1'b1; b=1'b1; c=1'b1; d=1'b0;
    #10
    a=1'b1; b=1'b1; c=1'b1; d=1'b1;
    #10
    $display("Test complete");
end
endmodule

DiSL Lab/Lab2/prog5_tb.vcd
$date
	Thu Aug  6 10:07:23 2026
$end
$version
	Icarus Verilog
$end
$timescale
	1ns
$end
$scope module prog5_tb $end
$var wire 1 ! f $end
$var reg 1 " a $end
$var reg 1 # b $end
$var reg 1 $ c $end
$var reg 1 % d $end
$scope module p5 $end
$var wire 1 " a $end
$var wire 1 # b $end
$var wire 1 $ c $end
$var wire 1 % d $end
$var wire 1 ! f $end
$upscope $end
$upscope $end
$enddefinitions $end
#0
$dumpvars
0%
0$
0#
0"
0!
$end
#10
1%
#20
0%
1$
#30
1%
#40
0%
0$
1#
#50
1%
#60
0%
1$
#70
1!
1%
#80
0!
0%
0$
0#
1"
#90
1%
#100
0%
1$
#110
1!
1%
#120
0!
0%
0$
1#
#130
1!
1%
#140
0%
1$
#150
1%
