DiSL Lab/Lab2/prog2.v
module prog2(a, b, c, d, f);
	input a, b, c, d;
	output f;

	//Gate level primitives
	not (h, b);
	not (i, c);
	not (j, d);
	and (p, b, i, j);
	and (q, h, c);
	and (r, h, d);
	or (f, p, q, r);
endmodule

DiSL Lab/Lab3/prog2_tb.v
`timescale 1ns/1ns
`include "prog2.v"//Name of the Verilog file
module prog2_tb();
reg a, b, c, d;//Input
wire f;//Output
prog2 p2(a, b, c, d, f); //Instantiation of the module
initial
begin
    $dumpfile("prog2_tb.vcd");
    $dumpvars(0, prog2_tb);
    a=1'b0; b=1'b0; c=1'b0; d=1'b0;
    #10
    a=1'b0; b=1'b0; c=1'b0; d=1'b1;
    #10
    a=1'b0; b=1'b0; c=1'b1; d=1'b0;
    #10
    a=1'b0; b=1'b0; c=1'b1; d=1'b1;
    #10
    a=1'b0; b=1'b1; c=1'b0; d=1'b0;
    #10
    a=1'b0; b=1'b1; c=1'b0; d=1'b1;
    #10
    a=1'b0; b=1'b1; c=1'b1; d=1'b0;
    #10
    a=1'b0; b=1'b1; c=1'b1; d=1'b1;
    #10
    a=1'b1; b=1'b0; c=1'b0; d=1'b0;
    #10
    a=1'b1; b=1'b0; c=1'b0; d=1'b1;
    #10
    a=1'b1; b=1'b0; c=1'b1; d=1'b0;
    #10
    a=1'b1; b=1'b0; c=1'b1; d=1'b1;
    #10
    a=1'b1; b=1'b1; c=1'b0; d=1'b0;
    #10
    a=1'b1; b=1'b1; c=1'b0; d=1'b1;
    #10
    a=1'b1; b=1'b1; c=1'b1; d=1'b0;
    #10
    a=1'b1; b=1'b1; c=1'b1; d=1'b1;
    #10
    $display("Test complete");
end
endmodule

DiSL Lab/Lab2/prog2_tb.vcd
$date
	Thu Aug  6 09:30:40 2026
$end
$version
	Icarus Verilog
$end
$timescale
	1ns
$end
$scope module prog2_tb $end
$var wire 1 ! f $end
$var reg 1 " a $end
$var reg 1 # b $end
$var reg 1 $ c $end
$var reg 1 % d $end
$scope module p2 $end
$var wire 1 " a $end
$var wire 1 # b $end
$var wire 1 $ c $end
$var wire 1 % d $end
$var wire 1 ! f $end
$var wire 1 & h $end
$var wire 1 ' i $end
$var wire 1 ( j $end
$var wire 1 ) p $end
$var wire 1 * q $end
$var wire 1 + r $end
$upscope $end
$upscope $end
$enddefinitions $end
#0
$dumpvars
0+
0*
0)
1(
1'
1&
0%
0$
0#
0"
0!
$end
#10
1!
0(
1+
1%
#20
1(
0+
0'
1*
0%
1$
#30
0(
1+
1%
#40
1)
1!
1(
0+
1'
0*
0&
0%
0$
1#
#50
0!
0)
0(
1%
#60
1(
0'
0%
1$
#70
0(
1%
#80
1(
1'
1&
0%
0$
0#
1"
#90
1!
0(
1+
1%
#100
1(
0+
0'
1*
0%
1$
#110
0(
1+
1%
#120
1)
1!
1(
0+
1'
0*
0&
0%
0$
1#
#130
0!
0)
0(
1%
#140
1(
0'
0%
1$
#150
0(
1%
