DiSL Lab/Lab6/prog3.v
module decoder2to4(A,en,Y);

input [1:0] A;
input en;
output reg [3:0] Y;

always @(*)
begin
    Y=4'b1111;

    if(en)
    begin
        case(A)
            2'b00: Y=4'b1110;
            2'b01: Y=4'b1101;
            2'b10: Y=4'b1011;
            2'b11: Y=4'b0111;
        endcase
    end
end

endmodule


module decoder4to16(A,en,Y);

input [3:0] A;
input en;
output [15:0] Y;
wire [3:0] E;

decoder2to4 d1(A[3:2],en,E);

decoder2to4 d2(A[1:0],~E[0],Y[3:0]);
decoder2to4 d3(A[1:0],~E[1],Y[7:4]);
decoder2to4 d4(A[1:0],~E[2],Y[11:8]);
decoder2to4 d5(A[1:0],~E[3],Y[15:12]);

endmodule

DiSL Lab/Lab6/prog3_tb.v
`timescale 1ns/1ns
`include "prog3.v"

module prog3_tb();

reg [3:0] A;
reg en;
wire [15:0] Y;

decoder4to16 ex1(A,en,Y);

initial
begin
$dumpfile("prog3_tb.vcd");
$dumpvars(0,prog3_tb);

en=1'b1;

A=4'b0000;
#20;
A=4'b0001;
#20;
A=4'b0010;
#20;
A=4'b0011;
#20;
A=4'b0100;
#20;
A=4'b0101;
#20;
A=4'b0110;
#20;
A=4'b0111;
#20;
A=4'b1000;
#20;
A=4'b1001;
#20;
A=4'b1010;
#20;
A=4'b1011;
#20;
A=4'b1100;
#20;
A=4'b1101;
#20;
A=4'b1110;
#20;
A=4'b1111;
#20;

$display("Test Complete");
end

endmodule

DiSL Lab/Lab6/prog3_tb.vcd
$date
	Thu Sep  3 10:10:21 2026
$end
$version
	Icarus Verilog
$end
$timescale
	1ns
$end
$scope module prog3_tb $end
$var wire 16 ! Y [15:0] $end
$var reg 4 " A [3:0] $end
$var reg 1 # en $end
$scope module ex1 $end
$var wire 4 $ A [3:0] $end
$var wire 1 # en $end
$var wire 16 % Y [15:0] $end
$var wire 4 & E [3:0] $end
$scope module d1 $end
$var wire 2 ' A [1:0] $end
$var wire 1 # en $end
$var reg 4 ( Y [3:0] $end
$upscope $end
$scope module d2 $end
$var wire 2 ) A [1:0] $end
$var wire 1 * en $end
$var reg 4 + Y [3:0] $end
$upscope $end
$scope module d3 $end
$var wire 2 , A [1:0] $end
$var wire 1 - en $end
$var reg 4 . Y [3:0] $end
$upscope $end
$scope module d4 $end
$var wire 2 / A [1:0] $end
$var wire 1 0 en $end
$var reg 4 1 Y [3:0] $end
$upscope $end
$scope module d5 $end
$var wire 2 2 A [1:0] $end
$var wire 1 3 en $end
$var reg 4 4 Y [3:0] $end
$upscope $end
$upscope $end
$upscope $end
$enddefinitions $end
#0
$dumpvars
b1111 4
03
b0 2
b1111 1
00
b0 /
b1111 .
0-
b0 ,
b1110 +
1*
b0 )
b1110 (
b0 '
b1110 &
b1111111111111110 %
b0 $
1#
b0 "
b1111111111111110 !
$end
#20
b1111111111111101 !
b1111111111111101 %
b1101 +
b1 )
b1 ,
b1 /
b1 2
b1 "
b1 $
#40
b1111111111111011 !
b1111111111111011 %
b1011 +
b10 )
b10 ,
b10 /
b10 2
b10 "
b10 $
#60
b1111111111110111 !
b1111111111110111 %
b111 +
b11 )
b11 ,
b11 /
b11 2
b11 "
b11 $
#80
b1110 .
1-
0*
b1101 &
b1101 (
b1111111111101111 !
b1111111111101111 %
b1111 +
b1 '
b0 )
b0 ,
b0 /
b0 2
b100 "
b100 $
#100
b1111111111011111 !
b1111111111011111 %
b1101 .
b1 )
b1 ,
b1 /
b1 2
b101 "
b101 $
#120
b1111111110111111 !
b1111111110111111 %
b1011 .
b10 )
b10 ,
b10 /
b10 2
b110 "
b110 $
#140
b1111111101111111 !
b1111111101111111 %
b111 .
b11 )
b11 ,
b11 /
b11 2
b111 "
b111 $
#160
b1110 1
10
0-
b1011 &
b1011 (
b1111111011111111 !
b1111111011111111 %
b1111 .
b10 '
b0 )
b0 ,
b0 /
b0 2
b1000 "
b1000 $
#180
b1111110111111111 !
b1111110111111111 %
b1101 1
b1 )
b1 ,
b1 /
b1 2
b1001 "
b1001 $
#200
b1111101111111111 !
b1111101111111111 %
b1011 1
b10 )
b10 ,
b10 /
b10 2
b1010 "
b1010 $
#220
b1111011111111111 !
b1111011111111111 %
b111 1
b11 )
b11 ,
b11 /
b11 2
b1011 "
b1011 $
#240
b1110 4
13
00
b111 &
b111 (
b1110111111111111 !
b1110111111111111 %
b1111 1
b11 '
b0 )
b0 ,
b0 /
b0 2
b1100 "
b1100 $
#260
b1101111111111111 !
b1101111111111111 %
b1101 4
b1 )
b1 ,
b1 /
b1 2
b1101 "
b1101 $
#280
b1011111111111111 !
b1011111111111111 %
b1011 4
b10 )
b10 ,
b10 /
b10 2
b1110 "
b1110 $
#300
b111111111111111 !
b111111111111111 %
b111 4
b11 )
b11 ,
b11 /
b11 2
b1111 "
b1111 $
