DiSL Lab/Lab6/prog2.v
module decoder3to8(A,en,Y);

input [2:0] A;
input en;
output reg [7:0] Y;
integer i;

always @(*)
begin
    Y=8'b00000000;

    if(en)
        for(i=0;i<8;i=i+1)
            if(A==i) Y[i]=1'b1;
end

endmodule


module decoder4to16(A,en,Y);

input [3:0] A;
input en;
output [15:0] Y;

decoder3to8 d1(A[2:0],en&~A[3],Y[7:0]);
decoder3to8 d2(A[2:0],en&A[3],Y[15:8]);

endmodule

DiSL Lab/Lab6/prog2_tb.v
`timescale 1ns/1ns
`include "prog2.v"

module prog2_tb();

reg [3:0] A;
reg en;
wire [15:0] Y;

decoder4to16 ex1(A,en,Y);

initial
begin
$dumpfile("prog2_tb.vcd");
$dumpvars(0,prog2_tb);

en=1'b1;

A=4'b0000;
#20;
A=4'b0001;
#20;
A=4'b0010;
#20;
A=4'b0011;
#20;
A=4'b0100;
#20;
A=4'b0101;
#20;
A=4'b0110;
#20;
A=4'b0111;
#20;
A=4'b1000;
#20;
A=4'b1001;
#20;
A=4'b1010;
#20;
A=4'b1011;
#20;
A=4'b1100;
#20;
A=4'b1101;
#20;
A=4'b1110;
#20;
A=4'b1111;
#20;

$display("Test Complete");
end

endmodule

DiSL Lab/Lab6/prog2_tb.vcd
$date
	Thu Sep  3 10:10:09 2026
$end
$version
	Icarus Verilog
$end
$timescale
	1ns
$end
$scope module prog2_tb $end
$var wire 16 ! Y [15:0] $end
$var reg 4 " A [3:0] $end
$var reg 1 # en $end
$scope module ex1 $end
$var wire 4 $ A [3:0] $end
$var wire 1 # en $end
$var wire 16 % Y [15:0] $end
$scope module d1 $end
$var wire 3 & A [2:0] $end
$var wire 1 ' en $end
$var reg 8 ( Y [7:0] $end
$var integer 32 ) i [31:0] $end
$upscope $end
$scope module d2 $end
$var wire 3 * A [2:0] $end
$var wire 1 + en $end
$var reg 8 , Y [7:0] $end
$var integer 32 - i [31:0] $end
$upscope $end
$upscope $end
$upscope $end
$enddefinitions $end
#0
$dumpvars
bx -
b0 ,
0+
b0 *
b1000 )
b1 (
1'
b0 &
b1 %
b0 $
1#
b0 "
b1 !
$end
#20
b1000 )
b10 !
b10 %
b10 (
b1 &
b1 *
b1 "
b1 $
#40
b1000 )
b100 !
b100 %
b100 (
b10 &
b10 *
b10 "
b10 $
#60
b1000 )
b1000 !
b1000 %
b1000 (
b11 &
b11 *
b11 "
b11 $
#80
b1000 )
b10000 !
b10000 %
b10000 (
b100 &
b100 *
b100 "
b100 $
#100
b1000 )
b100000 !
b100000 %
b100000 (
b101 &
b101 *
b101 "
b101 $
#120
b1000 )
b1000000 !
b1000000 %
b1000000 (
b110 &
b110 *
b110 "
b110 $
#140
b1000 )
b10000000 !
b10000000 %
b10000000 (
b111 &
b111 *
b111 "
b111 $
#160
0'
b1000 )
b0 (
b100000000 !
b100000000 %
b1 ,
b1000 -
1+
b0 &
b0 *
b1000 "
b1000 $
#180
b1000 -
b1000000000 !
b1000000000 %
b10 ,
b1 &
b1 *
b1001 "
b1001 $
#200
b1000 -
b10000000000 !
b10000000000 %
b100 ,
b10 &
b10 *
b1010 "
b1010 $
#220
b1000 -
b100000000000 !
b100000000000 %
b1000 ,
b11 &
b11 *
b1011 "
b1011 $
#240
b1000 -
b1000000000000 !
b1000000000000 %
b10000 ,
b100 &
b100 *
b1100 "
b1100 $
#260
b1000 -
b10000000000000 !
b10000000000000 %
b100000 ,
b101 &
b101 *
b1101 "
b1101 $
#280
b1000 -
b100000000000000 !
b100000000000000 %
b1000000 ,
b110 &
b110 *
b1110 "
b1110 $
#300
b1000 -
b1000000000000000 !
b1000000000000000 %
b10000000 ,
b111 &
b111 *
b1111 "
b1111 $
