DiSL Lab/Lab4/prog1.v
//==============================
// HALF ADDER
//==============================
module half_adder(A, B, Sum, Carry);
    input  A, B;
    output Sum, Carry;
    assign Sum   = A ^ B;
    assign Carry = A & B;
endmodule


//==============================
// FULL ADDER
//==============================
module full_adder(A, B, Cin, Cout, Sum);
    input  A, B, Cin;
    output Sum, Cout;
    assign Sum  = A ^ B ^ Cin;
    assign Cout = (A & B) | (B & Cin) | (A & Cin);
endmodule

DiSL Lab/Lab4/prog1_tb.v
`timescale 1ns/1ns
`include "prog1.v"//Name of the Verilog file
module prog1_tb();
reg A, B, Cin;
wire HA_Sum, HA_Carry;
wire FA_Sum, FA_Cout;

half_adder HA(A, B, HA_Sum, HA_Carry);
full_adder FA(A, B, Cin, FA_Sum, FA_Cout);
initial
begin
    $dumpfile("prog1_tb.vcd");
    $dumpvars(0, prog1_tb);
    A=1'b0; B=1'b0; Cin=1'b0;
    #10
    A=1'b0; B=1'b0; Cin=1'b1;
    #10
    A=1'b0; B=1'b1; Cin=1'b0;
    #10
    A=1'b0; B=1'b1; Cin=1'b1;
    #10
    A=1'b1; B=1'b0; Cin=1'b0;
    #10
    A=1'b1; B=1'b0; Cin=1'b1;
    #10
    A=1'b1; B=1'b1; Cin=1'b0;
    #10
    A=1'b1; B=1'b1; Cin=1'b1;
    #10
    $display("Test complete");
end
endmodule

DiSL Lab/Lab4/prog1_tb.vcd
$date
	Thu Aug 20 09:43:49 2026
$end
$version
	Icarus Verilog
$end
$timescale
	1ns
$end
$scope module prog1_tb $end
$var wire 1 ! HA_Sum $end
$var wire 1 " HA_Carry $end
$var wire 1 # FA_Sum $end
$var wire 1 $ FA_Cout $end
$var reg 1 % A $end
$var reg 1 & B $end
$var reg 1 ' Cin $end
$scope module FA $end
$var wire 1 % A $end
$var wire 1 & B $end
$var wire 1 ' Cin $end
$var wire 1 # Cout $end
$var wire 1 $ Sum $end
$upscope $end
$scope module HA $end
$var wire 1 % A $end
$var wire 1 & B $end
$var wire 1 " Carry $end
$var wire 1 ! Sum $end
$upscope $end
$upscope $end
$enddefinitions $end
#0
$dumpvars
0'
0&
0%
0$
0#
0"
0!
$end
#10
1$
1'
#20
1!
0'
1&
#30
1#
0$
1'
#40
0#
1$
0'
0&
1%
#50
1#
0$
1'
#60
0!
1"
0'
1&
#70
1$
1'
